snek/__init__.py
snek/abc.py
snek/bot.py
snek/exceptions.py
snek/cogs/__init__.py
snek/cogs/database.py
snek/cogs/identity.py
d_snek-1.2.8.dist-info/LICENSE
d_snek-1.2.8.dist-info/METADATA
d_snek-1.2.8.dist-info/WHEEL
d_snek-1.2.8.dist-info/top_level.txt
d_snek-1.2.8.dist-info/RECORD
