Metadata-Version: 2.1
Name: d-snek
Version: 1.2.8
Summary: Discord SNEK framework
Home-page: https://git.jboi.dev/ShadowJonathan/SNEK
Author: Jonathan de Jong
Author-email: jonathan@automatia.nl
License: UNKNOWN
Platform: UNKNOWN
Classifier: Programming Language :: Python :: 3
Classifier: License :: OSI Approved :: MIT License
Classifier: Operating System :: OS Independent
Requires-Python: >=3.6
Requires-Dist: discord.py (>=1.2.5)
Requires-Dist: pony
Requires-Dist: environs
Requires-Dist: dataclasses ; python_version < "3.7"
Provides-Extra: dev
Requires-Dist: ipython ; extra == 'dev'
Requires-Dist: twine ; extra == 'dev'
Requires-Dist: pymysql ; extra == 'dev'
Requires-Dist: tox ; extra == 'dev'
Requires-Dist: bump2version ; extra == 'dev'
Provides-Extra: lint
Requires-Dist: flake8 (==3.7.9) ; extra == 'lint'
Requires-Dist: isort (==4.3.21) ; extra == 'lint'
Requires-Dist: mypy (==0.740) ; extra == 'lint'
Requires-Dist: black (==19.10b0) ; extra == 'lint'
Requires-Dist: flake8-bugbear (<20,>=19.8.0) ; extra == 'lint'
Requires-Dist: docformatter (<2,>=1.3.1) ; extra == 'lint'
